mkdocs_drawio/plugin.py
mkdocs_drawio_km-1.7.2.dist-info/LICENSE
mkdocs_drawio_km-1.7.2.dist-info/METADATA
mkdocs_drawio_km-1.7.2.dist-info/WHEEL
mkdocs_drawio_km-1.7.2.dist-info/entry_points.txt
mkdocs_drawio_km-1.7.2.dist-info/RECORD
