Metadata-Version: 2.1
Name: mkdocs-drawio-km
Version: 1.7.2
Summary: MkDocs plugin for embedding Drawio files
Home-page: https://github.com/tuunit/mkdocs-drawio/
License: MIT
Keywords: mkdocs,plugin,markdown,drawio,kity,minder
Author: Shao,ShunZhong
Author-email: tempestwin@163.com
Requires-Python: >=3.7.0,<4.0.0
Classifier: License :: OSI Approved :: MIT License
Classifier: Programming Language :: Python :: 3
Classifier: Programming Language :: Python :: 3.7
Classifier: Programming Language :: Python :: 3.8
Classifier: Programming Language :: Python :: 3.9
Classifier: Programming Language :: Python :: 3.10
Classifier: Programming Language :: Python :: 3.11
Classifier: Programming Language :: Python :: 3.12
Classifier: Programming Language :: Python :: 3.13
Requires-Dist: Jinja2 (>=3.0)
Requires-Dist: beautifulsoup4 (>=4.0)
Requires-Dist: lxml (>=4.0)
Requires-Dist: mkdocs (>=1.3)
Requires-Dist: requests (>=2.0)
Project-URL: Repository, https://github.com/tuunit/mkdocs-drawio/
